[
    {
        "count":2764,
        "seg":"好吃"
    },
    {
        "count":1005,
        "seg":"吃"
    },
    {
        "count":786,
        "seg":"服務"
    },
    {
        "count":727,
        "seg":"不錯"
    },
    {
        "count":537,
        "seg":"新鮮"
    },
    {
        "count":495,
        "seg":"價格"
    },
    {
        "count":492,
        "seg":"餐點"
    },
    {
        "count":457,
        "seg":"非常"
    },
    {
        "count":436,
        "seg":"味道"
    },
    {
        "count":410,
        "seg":"便宜"
    },
    {
        "count":407,
        "seg":"環境"
    },
    {
        "count":399,
        "seg":"口味"
    },
    {
        "count":369,
        "seg":"用餐"
    },
    {
        "count":367,
        "seg":"湯頭"
    },
    {
        "count":363,
        "seg":"親切"
    },
    {
        "count":348,
        "seg":"基隆"
    },
    {
        "count":337,
        "seg":"老闆"
    },
    {
        "count":336,
        "seg":"真的"
    },
    {
        "count":332,
        "seg":"美味"
    },
    {
        "count":317,
        "seg":"態度"
    },
    {
        "count":314,
        "seg":"海鮮"
    },
    {
        "count":283,
        "seg":"東西"
    },
    {
        "count":282,
        "seg":"份量"
    },
    {
        "count":278,
        "seg":"餐廳"
    },
    {
        "count":277,
        "seg":"cp值"
    },
    {
        "count":272,
        "seg":"推薦"
    },
    {
        "count":266,
        "seg":"食材"
    },
    {
        "count":254,
        "seg":"高"
    },
    {
        "count":242,
        "seg":"沒"
    },
    {
        "count":240,
        "seg":"覺得"
    },
    {
        "count":238,
        "seg":"有點"
    },
    {
        "count":235,
        "seg":"不會"
    },
    {
        "count":230,
        "seg":"麵"
    },
    {
        "count":229,
        "seg":"牛肉"
    },
    {
        "count":217,
        "seg":"牛肉麵"
    },
    {
        "count":215,
        "seg":"料理"
    },
    {
        "count":213,
        "seg":"值得"
    },
    {
        "count":205,
        "seg":"乾淨"
    },
    {
        "count":202,
        "seg":"不錯吃"
    },
    {
        "count":202,
        "seg":"超"
    },
    {
        "count":200,
        "seg":"食物"
    },
    {
        "count":199,
        "seg":"感覺"
    },
    {
        "count":199,
        "seg":"店家"
    },
    {
        "count":199,
        "seg":"喜歡"
    },
    {
        "count":196,
        "seg":"比較"
    },
    {
        "count":186,
        "seg":"價位"
    },
    {
        "count":185,
        "seg":"實在"
    },
    {
        "count":183,
        "seg":"炒飯"
    },
    {
        "count":182,
        "seg":"肉"
    },
    {
        "count":181,
        "seg":"平價"
    },
    {
        "count":177,
        "seg":"人員"
    },
    {
        "count":172,
        "seg":"普通"
    },
    {
        "count":171,
        "seg":"菜色"
    },
    {
        "count":170,
        "seg":"很多"
    },
    {
        "count":168,
        "seg":"麵包"
    },
    {
        "count":163,
        "seg":"特別"
    },
    {
        "count":161,
        "seg":"適合"
    },
    {
        "count":160,
        "seg":"店員"
    },
    {
        "count":157,
        "seg":"很棒"
    },
    {
        "count":156,
        "seg":"讚"
    }
]