[
    {
        "city": "Taipei",
        "word_list": [
            {
                "seg": "好吃",
                "count": 225482
            },
            {
                "seg": "服務",
                "count": 138697
            },
            {
                "seg": "不錯",
                "count": 87483
            },
            {
                "seg": "餐點",
                "count": 73612
            },
            {
                "seg": "價格",
                "count": 59333
            },
            {
                "seg": "美味",
                "count": 53196
            },
            {
                "seg": "環境",
                "count": 51843
            },
            {
                "seg": "味道",
                "count": 50870
            },
            {
                "seg": "用餐",
                "count": 44500
            },
            {
                "seg": "很好",
                "count": 43141
            },
            {
                "seg": "新鮮",
                "count": 42243
            },
            {
                "seg": "口味",
                "count": 41674
            },
            {
                "seg": "很好吃",
                "count": 39806
            },
            {
                "seg": "親切",
                "count": 37870
            },
            {
                "seg": "態度",
                "count": 31951
            },
            {
                "seg": "食材",
                "count": 31476
            },
            {
                "seg": "份量",
                "count": 31138
            },
            {
                "seg": "料理",
                "count": 31003
            },
            {
                "seg": "推薦",
                "count": 29941
            },
            {
                "seg": "氣氛",
                "count": 29883
            },
            {
                "seg": "很棒",
                "count": 29688
            },
            {
                "seg": "人員",
                "count": 29245
            },
            {
                "seg": "喜歡",
                "count": 27513
            },
            {
                "seg": "cp值",
                "count": 24989
            },
            {
                "seg": "適合",
                "count": 24608
            },
            {
                "seg": "湯頭",
                "count": 22770
            },
            {
                "seg": "菜色",
                "count": 22526
            },
            {
                "seg": "值得",
                "count": 22183
            },
            {
                "seg": "讚",
                "count": 21428
            },
            {
                "seg": "價位",
                "count": 20210
            },
            {
                "seg": "普通",
                "count": 19474
            },
            {
                "seg": "感覺",
                "count": 19219
            },
            {
                "seg": "牛肉",
                "count": 18997
            },
            {
                "seg": "特別",
                "count": 18973
            },
            {
                "seg": "舒適",
                "count": 18562
            },
            {
                "seg": "時間",
                "count": 17418
            },
            {
                "seg": "聚餐",
                "count": 16737
            },
            {
                "seg": "不錯吃",
                "count": 16323
            },
            {
                "seg": "海鮮",
                "count": 15910
            },
            {
                "seg": "佳",
                "count": 15628
            },
            {
                "seg": "朋友",
                "count": 15565
            },
            {
                "seg": "品質",
                "count": 15025
            },
            {
                "seg": "個人",
                "count": 14782
            },
            {
                "seg": "便宜",
                "count": 14452
            },
            {
                "seg": "乾淨",
                "count": 13907
            },
            {
                "seg": "咖哩",
                "count": 13776
            },
            {
                "seg": "甜點",
                "count": 13720
            }
        ]
    }
]